FPAdder/fp32_norm.v
`timescale 1ns / 1ps

/* Normalization */
module fadd_norm (
	input sign,			// result sign
	input [7:0] temp_exp,	// temp exponent
	input [27:0] cal_frac,	// fraction before normalization
	output [31:0] s);		// result
	
	wire [26:0] f4, f3, f2, f1, f0;
	
	// 從左邊找到第一個1
	wire [4:0] zeros;	// 左邊數起有幾個0
	assign zeros[4] = ~|cal_frac[26:11];	// 16-bit 0
	assign f4 = zeros[4]? {cal_frac[10:0],16'b0} : cal_frac[26:0];
	assign zeros[3] = ~|f4[26:19];			// 8-bit 0
	assign f3 = zeros[3]? {f4[18:0], 8'b0} : f4;
	assign zeros[2] = ~|f3[26:23];			// 4-bit 0
	assign f2 = zeros[2]? {f3[22:0], 4'b0} : f3;
	assign zeros[1] = ~|f2[26:25];			// 2-bit 0
	assign f1 = zeros[1]? {f2[24:0], 2'b0} : f2;
	assign zeros[0] = ~f1[26];				// 1-bit 0
	assign f0 = zeros[0]? {f1[25:0], 1'b0} : f1;
	reg [26:0] frac0;
	reg [7:0] exp0;
	
	// 位移以及修改exponent
	always @ * begin
		if (cal_frac==0) begin	// Result is 0
			frac0 = 0;
			exp0 = 0;
		end
		else if (cal_frac[27]) begin
			frac0 = cal_frac[27:1];	// 1x.xxxxxxxxxxxxxxxxxxxxxxx xx
			exp0 = temp_exp + 8'h1; // ->1.xxxxxxxxxxxxxxxxxxxxxxx xxx
		end
		else begin
			exp0 = temp_exp - zeros;
			frac0 = f0; // 01.xxxxxxxxxxxxxxxxxxxxxxx xxx
			
		end
	end
	
	// Rounding
	wire frac_plus_1 =
	frac0[2] & (frac0[1] | frac0[0]) |
	frac0[2] & ~frac0[1] & ~frac0[0] & frac0[3];

	wire [24:0] frac_round = {1'b0, frac0[26:3]} + frac_plus_1;
	wire [7:0] exponent = frac_round[24] ?
							exp0 + 8'h1 :
							exp0;
	
	assign s = {sign, exponent, frac_round[22:0]};
endmodule

FPAdder/fp32_cal.v
`timescale 1ns / 1ps

/* Calculation */
module fadd_cal (	
	input op_sub,
	input [23:0] large_frac24,
	input [26:0] small_frac27,
	output [27:0] cal_frac);

	//補上grs, 以及避免溢位狀況, 共28bit
	wire [27:0] aligned_large_frac = {1'b0, large_frac24, 3'b000};
	wire [27:0] aligned_small_frac = {1'b0, small_frac27};
	
	//相減或相加
	assign cal_frac = op_sub?
		aligned_large_frac - aligned_small_frac :
		aligned_large_frac + aligned_small_frac;
endmodule

FPAdder/fp32_align.v
`timescale 1ns / 1ps

/* Alignment */
module fadd_align (		
	input [31:0] a, b,	// fp a and b
	input sub,			// add or sub
	output sign,			// result sign
	output [7:0] temp_exp,	// result exponent
	output op_sub,			// fraction operation
	output [23:0] large_frac24,		// fraction of large one
	output [26:0] small_frac27);	// fraction of small one

	// 不看sign bit,判斷a or b大
	wire exchange = (b[30:0] > a[30:0]);
	wire [31:0] fp_large = exchange? b : a;
	wire [31:0] fp_small = exchange? a : b;

	// 轉成1.f格式
	wire fp_large_hidden_bit = |fp_large[30:23];
	wire fp_small_hidden_bit = |fp_small[30:23];
	wire [23:0] large_frac24 = {fp_large_hidden_bit, fp_large[22:0]};
	wire [23:0] small_frac24 = {fp_small_hidden_bit, fp_small[22:0]};

	// 儲存較大數的exponent
	assign temp_exp = fp_large[30:23];

	// 判斷結果值正負
	assign sign = exchange ? sub^b[31] : a[31];
	
	// fraction運算使用加法或減法
	assign op_sub = sub ^ fp_large[31] ^ fp_small[31];
	
	// ea-eb
	wire [7:0] exp_diff = fp_large[30:23] - fp_small[30:23];
	
	// 計算需要位移幾位, 並且位移
	wire [49:0] small_frac50 = (exp_diff >= 26) ? 
								{26'h0, small_frac24} : 
								{small_frac24, 26'h0} >> exp_diff;
	
	// 留下24bit以及保護.循環位, 計算多出來的位數, 使用reduction OR簡化成1bit
	assign small_frac27 = {small_frac50[49:24], |small_frac50[23:0]};
endmodule

FPAdder/fp32_adder.v
`include "fp32_align.v"
`include "fp32_cal.v"
`include "fp32_norm.v"
`timescale 1ns / 1ps

module fpadder (		// fp adder
	input [31:0] a, b,	// fp a and b
	input sub,			// 1: sub; 0: add
	output [31:0] s); 	// fp output
	
	wire a_sign;
	wire [7:0] a_exp;
	wire a_op_sub;
	wire [26:0] a_small_frac;
	wire [23:0] a_large_frac;

	// Alignment
	fadd_align alignment (
		.a(a),
		.b(b),
		.sub(sub),
		.sign(a_sign), 		// sign of large one
		.temp_exp(a_exp),	// exponent of large one
		.op_sub(a_op_sub),	// add or sub
		.large_frac24(a_large_frac),	// fraction of large one
		.small_frac27(a_small_frac));	// fraction of small one
	
	// Calculation
	wire [27:0] c_frac;
	fadd_cal calculation (
		.op_sub(a_op_sub),
		.large_frac24(a_large_frac),
		.small_frac27(a_small_frac),
		.cal_frac(c_frac));	// result fraction

	// Normalization
	fadd_norm normalization (
		.sign(a_sign),		// result sign
		.temp_exp(a_exp),	// result exponent
		.cal_frac(c_frac),	// result fraction
		.s(s));				// result after normalization
endmodule

FPAdder/testbench_32bits.v
`include "fp32_adder.v"
`timescale 1ns / 1ps

module test_bench;

	/* Variables Declaration */
	reg[31:0] testInput_a;
	reg[31:0] testInput_b;
	reg [31:0] correct_ans;
	wire [31:0] adder_ans;
	/* Variables Declaration */

	/* 待驗證的Module */
	fpadder test(
		.a(testInput_a),
		.b(testInput_b),
		.sub(1'b0),
		.s(adder_ans));

	reg [4:0] cnt_test, cnt_right;
	initial begin
		$dumpfile("adder32.vcd");
		$dumpvars;

		#0
			cnt_test = 0;
			cnt_right = 0;
		
		#1	/********* Test Pattern *********/
			testInput_a = 32'hBA9DBB67;		// -0.0012034
			testInput_b = 32'h4148F5CB;		// 12.560008
			correct_ans = 32'h4148F0DD;		// 12.5588045
			cnt_test = cnt_test + 1;
		#10 
			if (adder_ans == correct_ans) begin
				success_case (testInput_a, testInput_b, correct_ans);
			end else begin
				failure_case (testInput_a, testInput_b, correct_ans, adder_ans);
			end
		
		#1	/********* Test Pattern *********/
			testInput_a = 32'h43E20FCC;		// 452.1234
			testInput_b = 32'hC1AC8ADB;		// -21.5678
			correct_ans = 32'h43D7471E;		// 430.5556
			cnt_test = cnt_test + 1;
		#10 
			if (adder_ans == correct_ans) begin
				success_case (testInput_a, testInput_b, correct_ans);
			end else begin
				failure_case (testInput_a, testInput_b, correct_ans, adder_ans);
			end
		
		#1	/********* Test Pattern *********/
			testInput_a = 32'hC49A522C;		// -1234.5679
			testInput_b = 32'h442987E6;		// 678.1234
			correct_ans = 32'hC40B1C72;		// -556.44446
			cnt_test = cnt_test + 1;
		#10 
			if (adder_ans == correct_ans) begin
				success_case (testInput_a, testInput_b, correct_ans);
			end else begin
				failure_case (testInput_a, testInput_b, correct_ans, adder_ans);
			end
		
		#1	/********* Test Pattern *********/
			testInput_a = 32'hA6AD6DA0;		// -1.2034E-15
			testInput_b = 32'h2BADAB89;		// 1.234E-12
			correct_ans = 32'h2BAD802E;		// 1.2327966E-12
			cnt_test = cnt_test + 1;
		#10 
			if (adder_ans == correct_ans) begin
				success_case (testInput_a, testInput_b, correct_ans);
			end else begin
				failure_case (testInput_a, testInput_b, correct_ans, adder_ans);
			end
        #1	/********* Test Pattern *********/
			testInput_a = 32'hD6DA0A6A;		// -1.1986913E-14
			testInput_b = 32'hDAB892BA;		// -2.5976362E-16
			correct_ans = 32'hDAB96CC4;		// -2.609623E-16
			cnt_test = cnt_test + 1;
		#10 
			if (adder_ans == correct_ans) begin
				success_case (testInput_a, testInput_b, correct_ans);
			end else begin
				failure_case (testInput_a, testInput_b, correct_ans, adder_ans);
			end
        #1	/********* Test Pattern *********/
			testInput_a = 32'h522CC49A;		// 1.855082E-11
			testInput_b = 32'h87E64429;		// -3.4646615E-34
			correct_ans = 32'h522CC49A;		// 1.855082E-11
			cnt_test = cnt_test + 1;
		#10 
			if (adder_ans == correct_ans) begin
				success_case (testInput_a, testInput_b, correct_ans);
			end else begin
				failure_case (testInput_a, testInput_b, correct_ans, adder_ans);
			end
        #1	/********* Test Pattern *********/
			testInput_a = 32'h0FCC43E2;		// 2.01421E-29
			testInput_b = 32'hC9DBC1AC;		// -1800245.5
			correct_ans = 32'hC9DBC1AC;		// -1800245.5
			cnt_test = cnt_test + 1;
		#10 
			if (adder_ans == correct_ans) begin
				success_case (testInput_a, testInput_b, correct_ans);
			end else begin
				failure_case (testInput_a, testInput_b, correct_ans, adder_ans);
			end
        #1	/********* Test Pattern *********/
			testInput_a = 32'hBB67BA9D;		// -3.5359033E-3
			testInput_b = 32'hF5CB4148;		// -5.1531266E-32
			correct_ans = 32'hF5CB4148;		// -5.1531266E-32
			cnt_test = cnt_test + 1;
		#10 
			if (adder_ans == correct_ans) begin
				success_case (testInput_a, testInput_b, correct_ans);
			end else begin
				failure_case (testInput_a, testInput_b, correct_ans, adder_ans);
			end
		#1	/********* Test Pattern *********/
			testInput_a = 32'h3B67BA9D;		// 3.5359033E-3
			testInput_b = 32'hBB67BA9D;		// -3.5359033E-3
			correct_ans = 32'h00000000;		// 0
			cnt_test = cnt_test + 1;
		#10 
			if (adder_ans == correct_ans) begin
				success_case (testInput_a, testInput_b, correct_ans);
			end else begin
				failure_case (testInput_a, testInput_b, correct_ans, adder_ans);
			end

		$finish;
	end



/*--------------- Standard Output for Success Case ---------------*/
task success_case;
input [31:0] testInput_a, testInput_b, correct_ans;
begin
	cnt_right = cnt_right + 1;

	$display ("Test %d ", cnt_test);
	$display ("///////////////////////");
	$display ("//// Successful %d ////", cnt_right);
	$display ("///////////////////////");
	$display ("%h + %h = ?", testInput_a, testInput_b);
	$display ("Answer = %h\n", correct_ans);
end endtask
/*--------------- Standard Output for Success Case ---------------*/



/*--------------- Standard Output for Failure Case ---------------*/
task failure_case;
input [31:0] testInput_a, testInput_b, correct_ans, result;
begin
	$display ("Test %d ", cnt_test);
	$display ("///////////////////////");
	$display ("///////// Fail ////////");
	$display ("///////////////////////");
	$display ("%h + %h = ?", testInput_a, testInput_b);
	$display ("your answer = %h", result);
	$display ("correct answer = %h\n", correct_ans);
end endtask
/*--------------- Standard Output for Failure Case ---------------*/

endmodule

FPAdder/adder32.vcd
$date
	Wed May  1 07:47:04 2019
$end
$version
	Icarus Verilog
$end
$timescale
	1ps
$end
$scope module test_bench $end
$var wire 32 ! adder_ans [31:0] $end
$var reg 5 " cnt_right [4:0] $end
$var reg 5 # cnt_test [4:0] $end
$var reg 32 $ correct_ans [31:0] $end
$var reg 32 % testInput_a [31:0] $end
$var reg 32 & testInput_b [31:0] $end
$scope module test $end
$var wire 32 ' a [31:0] $end
$var wire 32 ( b [31:0] $end
$var wire 1 ) sub $end
$var wire 32 * s [31:0] $end
$var wire 28 + c_frac [27:0] $end
$var wire 27 , a_small_frac [26:0] $end
$var wire 1 - a_sign $end
$var wire 1 . a_op_sub $end
$var wire 24 / a_large_frac [23:0] $end
$var wire 8 0 a_exp [7:0] $end
$scope module alignment $end
$var wire 32 1 a [31:0] $end
$var wire 32 2 b [31:0] $end
$var wire 1 . op_sub $end
$var wire 1 ) sub $end
$var wire 8 3 temp_exp [7:0] $end
$var wire 50 4 small_frac50 [49:0] $end
$var wire 27 5 small_frac27 [26:0] $end
$var wire 24 6 small_frac24 [23:0] $end
$var wire 1 - sign $end
$var wire 24 7 large_frac24 [23:0] $end
$var wire 1 8 fp_small_hidden_bit $end
$var wire 32 9 fp_small [31:0] $end
$var wire 1 : fp_large_hidden_bit $end
$var wire 32 ; fp_large [31:0] $end
$var wire 8 < exp_diff [7:0] $end
$var wire 1 = exchange $end
$upscope $end
$scope module calculation $end
$var wire 24 > large_frac24 [23:0] $end
$var wire 1 . op_sub $end
$var wire 27 ? small_frac27 [26:0] $end
$var wire 28 @ cal_frac [27:0] $end
$var wire 28 A aligned_small_frac [27:0] $end
$var wire 28 B aligned_large_frac [27:0] $end
$upscope $end
$scope module normalization $end
$var wire 28 C cal_frac [27:0] $end
$var wire 1 D frac_plus_1 $end
$var wire 1 - sign $end
$var wire 8 E temp_exp [7:0] $end
$var wire 5 F zeros [4:0] $end
$var wire 32 G s [31:0] $end
$var wire 25 H frac_round [24:0] $end
$var wire 27 I f4 [26:0] $end
$var wire 27 J f3 [26:0] $end
$var wire 27 K f2 [26:0] $end
$var wire 27 L f1 [26:0] $end
$var wire 27 M f0 [26:0] $end
$var wire 8 N exponent [7:0] $end
$var reg 8 O exp0 [7:0] $end
$var reg 27 P frac0 [26:0] $end
$upscope $end
$upscope $end
$scope task failure_case $end
$var reg 32 Q correct_ans [31:0] $end
$var reg 32 R result [31:0] $end
$var reg 32 S testInput_a [31:0] $end
$var reg 32 T testInput_b [31:0] $end
$upscope $end
$scope task success_case $end
$var reg 32 U correct_ans [31:0] $end
$var reg 32 V testInput_a [31:0] $end
$var reg 32 W testInput_b [31:0] $end
$upscope $end
$upscope $end
$enddefinitions $end
#0
$dumpvars
bx W
bx V
bx U
bx T
bx S
bx R
bx Q
bx P
bx O
bx N
bx M
bx L
bx K
bx J
bx I
bx H
bx G
bx F
bx E
xD
bx C
b0xxxxxxxxxxxxxxxxxxxxxxxx000 B
b0xxxxxxxxxxxxxxxxxxxxxxxxxxx A
bx @
bx ?
bx >
x=
bx <
bx ;
x:
bx 9
x8
bx 7
bx 6
bx 5
bx 4
bx 3
bx 2
bx 1
bx 0
bx /
x.
x-
bx ,
bx +
bx *
0)
bx (
bx '
bx &
bx %
bx $
b0 #
b0 "
bx !
$end
#1000
b110010001111000011011101 H
0D
b10000010 N
b10000010 O
b110010001111000011011101001 P
b110010001111000011011101001 M
b110010001111000011011101001 L
b110010001111000011011101001 K
b110010001111000011011101001 J
b110010001111000011011101001 I
b0 F
b110010001111000011011101001 +
b110010001111000011011101001 @
b110010001111000011011101001 C
1.
b10011101101111 A
b10011101101111 ,
b10011101101111 5
b10011101101111 ?
b1001110110111011011001110000000000000 4
1:
b1101 <
18
b1000001010010001111000011011101 !
b1000001010010001111000011011101 *
b1000001010010001111000011011101 G
0-
b110010001111010111001011000 B
b110010001111010111001011 /
b110010001111010111001011 7
b110010001111010111001011 >
b10000010 0
b10000010 3
b10000010 E
b100111011011101101100111 6
1=
b1000001010010001111010111001011 ;
b10111010100111011011101101100111 9
b1 #
b1000001010010001111000011011101 $
b1000001010010001111010111001011 &
b1000001010010001111010111001011 (
b1000001010010001111010111001011 2
b10111010100111011011101101100111 %
b10111010100111011011101101100111 '
b10111010100111011011101101100111 1
#11000
b1 "
b1000001010010001111000011011101 U
b1000001010010001111010111001011 W
b10111010100111011011101101100111 V
#12000
0D
b110101110100011100011110011 M
b110101110100011100011110011 L
b110101110100011100011110011 K
b110101110100011100011110 H
b110101110100011100011110011 J
b0 F
b110101110100011100011110011 P
b110101110100011100011110011 I
b1000011110101110100011100011110 !
b1000011110101110100011100011110 *
b1000011110101110100011100011110 G
b10000111 N
b10101100100010101101101 A
b10101100100010101101101 ,
b10101100100010101101101 5
b10101100100010101101101 ?
b110101110100011100011110011 +
b110101110100011100011110011 @
b110101110100011100011110011 C
b10000111 O
1.
b1010110010001010110110110000000000000000000000 4
b111000100000111111001100000 B
b111000100000111111001100 /
b111000100000111111001100 7
b111000100000111111001100 >
b10000111 0
b10000111 3
b10000111 E
b101011001000101011011011 6
b100 <
b1000011111000100000111111001100 ;
0=
b11000001101011001000101011011011 9
b10 #
b1000011110101110100011100011110 $
b11000001101011001000101011011011 &
b11000001101011001000101011011011 (
b11000001101011001000101011011011 2
b1000011111000100000111111001100 %
b1000011111000100000111111001100 '
b1000011111000100000111111001100 1
#22000
b10 "
b1000011110101110100011100011110 U
b11000001101011001000101011011011 W
b1000011111000100000111111001100 V
#23000
b1 F
b100010110001110001110010 H
b100010110001110001110010000 P
b100010110001110001110010000 M
b10001011000111000111001000 L
b10001011000111000111001000 K
b10001011000111000111001000 J
b10001011000111000111001000 I
b10001000 N
b10101001100001111110011000 A
b10101001100001111110011000 ,
b10101001100001111110011000 5
b10101001100001111110011000 ?
b10001011000111000111001000 +
b10001011000111000111001000 @
b10001011000111000111001000 C
b10001000 O
b1010100110000111111001100000000000000000000000000 4
b101010011000011111100110 6
b100110100101001000101100000 B
b100110100101001000101100 /
b100110100101001000101100 7
b100110100101001000101100 >
b10001001 0
b10001001 3
b10001001 E
b1 <
b11000100000010110001110001110010 !
b11000100000010110001110001110010 *
b11000100000010110001110001110010 G
1-
b1000100001010011000011111100110 9
b11000100100110100101001000101100 ;
b11 #
b11000100000010110001110001110010 $
b1000100001010011000011111100110 &
b1000100001010011000011111100110 (
b1000100001010011000011111100110 2
b11000100100110100101001000101100 %
b11000100100110100101001000101100 '
b11000100100110100101001000101100 1
#33000
b11 "
b11000100000010110001110001110010 U
b1000100001010011000011111100110 W
b11000100100110100101001000101100 V
#34000
1D
b0 F
b101011011000000000101101101 M
b101011011000000000101101101 L
b101011011000000000101101101 K
b101011011000000000101110 H
b101011011000000000101101101 J
b101011011000000000101101101 P
b101011011000000000101101101 I
b1010111 N
b10101101011011011 A
b10101101011011011 ,
b10101101011011011 5
b10101101011011011 ?
1.
b101011011000000000101101101 +
b101011011000000000101101101 @
b101011011000000000101101101 C
b1010111 O
b1010110101101101101000000000000000000000 4
b101011010110110110100000 6
b101011101011011000000000101110 !
b101011101011011000000000101110 *
b101011101011011000000000101110 G
0-
b101011011010101110001001000 B
b101011011010101110001001 /
b101011011010101110001001 7
b101011011010101110001001 >
b1010111 0
b1010111 3
b1010111 E
b1010 <
b10100110101011010110110110100000 9
1=
b101011101011011010101110001001 ;
b100 #
b101011101011011000000000101110 $
b101011101011011010101110001001 &
b101011101011011010101110001001 (
b101011101011011010101110001001 2
b10100110101011010110110110100000 %
b10100110101011010110110110100000 '
b10100110101011010110110110100000 1
#44000
b100 "
b101011101011011000000000101110 U
b101011101011011010101110001001 W
b10100110101011010110110110100000 V
#45000
b101110010110110011000100011 M
0D
b101110010110110011000100011 L
b101110010110110011000100011 K
b101110010110110011000100 H
b101110010110110011000100011 J
b101110010110110011000100011 P
b101110010110110011000100011 I
b10110101 N
0.
b1101101000001010011 A
b1101101000001010011 ,
b1101101000001010011 5
b1101101000001010011 ?
b101110010110110011000100011 +
b101110010110110011000100011 @
b101110010110110011000100011 C
b10110101 O
b11011010101110010110110011000100 !
b11011010101110010110110011000100 *
b11011010101110010110110011000100 G
1-
b110110100000101001101010000000000000000000 4
b101110001001001010111010000 B
b101110001001001010111010 /
b101110001001001010111010 7
b101110001001001010111010 >
b10110101 0
b10110101 3
b10110101 E
b110110100000101001101010 6
b1000 <
b11011010101110001001001010111010 ;
1=
b11010110110110100000101001101010 9
b101 #
b11011010101110010110110011000100 $
b11011010101110001001001010111010 &
b11011010101110001001001010111010 (
b11011010101110001001001010111010 2
b11010110110110100000101001101010 %
b11010110110110100000101001101010 '
b11010110110110100000101001101010 1
#55000
b101 "
b11011010101110010110110011000100 U
b11011010101110001001001010111010 W
b11010110110110100000101001101010 V
#56000
1D
b101011001100010010011010 H
b101011001100010010011001111 P
b101011001100010010011001111 M
b101011001100010010011001111 L
b101011001100010010011001111 K
b101011001100010010011001111 J
b101011001100010010011001111 I
b10100100 N
b1 A
b1 ,
b1 5
b1 ?
b101011001100010010011001111 +
b101011001100010010011001111 @
b101011001100010010011001111 C
b10100100 O
1.
b111001100100010000101001 4
b1010010001011001100010010011010 !
b1010010001011001100010010011010 *
b1010010001011001100010010011010 G
0-
b101011001100010010011010000 B
b101011001100010010011010 /
b101011001100010010011010 7
b101011001100010010011010 >
b10100100 0
b10100100 3
b10100100 E
b111001100100010000101001 6
b10010101 <
0=
b1010010001011001100010010011010 ;
b10000111111001100100010000101001 9
b110 #
b1010010001011001100010010011010 $
b10000111111001100100010000101001 &
b10000111111001100100010000101001 (
b10000111111001100100010000101001 2
b1010010001011001100010010011010 %
b1010010001011001100010010011010 '
b1010010001011001100010010011010 1
#66000
b110 "
b1010010001011001100010010011010 U
b10000111111001100100010000101001 W
b1010010001011001100010010011010 V
#67000
1D
b110110111100000110101100 H
b110110111100000110101011111 P
b110110111100000110101011111 M
b110110111100000110101011111 L
b110110111100000110101011111 K
b110110111100000110101011111 J
b110110111100000110101011111 I
1.
b10010011 N
b110110111100000110101011111 +
b110110111100000110101011111 @
b110110111100000110101011111 C
b10010011 O
b110011000100001111100010 4
b11001001110110111100000110101100 !
b11001001110110111100000110101100 *
b11001001110110111100000110101100 G
1-
b110011000100001111100010 6
b110110111100000110101100000 B
b110110111100000110101100 /
b110110111100000110101100 7
b110110111100000110101100 >
b10010011 0
b10010011 3
b10010011 E
b1110100 <
1=
b1111110011000100001111100010 9
b11001001110110111100000110101100 ;
b111 #
b11001001110110111100000110101100 $
b11001001110110111100000110101100 &
b11001001110110111100000110101100 (
b11001001110110111100000110101100 2
b1111110011000100001111100010 %
b1111110011000100001111100010 '
b1111110011000100001111100010 1
#77000
b111 "
b11001001110110111100000110101100 U
b11001001110110111100000110101100 W
b1111110011000100001111100010 V
#78000
0D
b110010110100000101001000 H
b110010110100000101001000001 P
b110010110100000101001000001 M
b110010110100000101001000001 L
b110010110100000101001000001 K
b110010110100000101001000001 J
b110010110100000101001000001 I
b11110101110010110100000101001000 !
b11110101110010110100000101001000 *
b11110101110010110100000101001000 G
b11101011 N
b110010110100000101001000001 +
b110010110100000101001000001 @
b110010110100000101001000001 C
b11101011 O
b111001111011101010011101 4
0.
b110010110100000101001000000 B
b110010110100000101001000 /
b110010110100000101001000 7
b110010110100000101001000 >
b11101011 0
b11101011 3
b11101011 E
b111001111011101010011101 6
b1110101 <
b11110101110010110100000101001000 ;
b10111011011001111011101010011101 9
b1000 #
b11110101110010110100000101001000 $
b11110101110010110100000101001000 &
b11110101110010110100000101001000 (
b11110101110010110100000101001000 2
b10111011011001111011101010011101 %
b10111011011001111011101010011101 '
b10111011011001111011101010011101 1
#88000
b1000 "
b11110101110010110100000101001000 U
b11110101110010110100000101001000 W
b10111011011001111011101010011101 V
#89000
b0 M
b0 L
b11111 F
b0 K
b0 H
b0 J
b0 P
b0 I
b0 N
b111001111011101010011101000 A
b111001111011101010011101000 ,
b111001111011101010011101000 5
b111001111011101010011101000 ?
b0 +
b0 @
b0 C
b0 O
b11100111101110101001110100000000000000000000000000 4
1.
b0 !
b0 *
b0 G
0-
b111001111011101010011101000 B
b111001111011101010011101 /
b111001111011101010011101 7
b111001111011101010011101 >
b1110110 0
b1110110 3
b1110110 E
b0 <
0=
b111011011001111011101010011101 ;
b10111011011001111011101010011101 9
b1001 #
b0 $
b10111011011001111011101010011101 &
b10111011011001111011101010011101 (
b10111011011001111011101010011101 2
b111011011001111011101010011101 %
b111011011001111011101010011101 '
b111011011001111011101010011101 1
#99000
b1001 "
b0 U
b10111011011001111011101010011101 W
b111011011001111011101010011101 V
