2019_DD_LAB10/labex/32mpy_booth.v
`timescale 1ns/1ps
module lab(CLK, RST, in_a, in_b, Product, Product_Valid,state);
input CLK, RST;
input signed[31:0]	in_a;	// Multiplicand
input signed[31:0]	in_b;// Multiplier
output reg signed [63:0] Product;
output reg Product_Valid;
input[1:0] state;


reg [31:0] Mplicand;
//reg [31:0] Mplier;
reg [6:0]	Counter ;
reg	sign;
reg Mythicalbit;

//Counter
always @(posedge CLK or posedge RST)
begin
	if(RST)
		Counter <=6'b0;
	else
		Counter <= Counter +6'b1;
end


//Multiplier
always @(posedge CLK or posedge RST)
begin
	//初始化數值
	if(RST) begin
		Product  <= 64'b0;
		Mplicand <= 32'b0;
		Mythicalbit <= 1'b0;
		//Mplier   <= 32'b0;	
	end 
	
	//輸入乘數與被乘數
	else if(Counter == 6'd0) begin
		if(state==2'b11) begin
			Mplicand <= in_a;
			Product <={32'b0,in_b};
			Mythicalbit <= 1'b0; 	// add 0 to the last bit of multiplier
		end
		else if(state==2'b10) begin
			Mplicand <= in_a;
			Product <={32'b0,in_a};
			Mythicalbit <= 1'b0; 	// add 0 to the last bit of multiplier
		end
		else if(state==2'b01) begin
			Mplicand <= in_b;
			Product <={32'b0,in_b};
			Mythicalbit <= 1'b0; 	// add 0 to the last bit of multiplier
		end
	end 
	
	//乘法與數值移位
	/* write down your design below */
	else if(Counter <=7'd32) 	// 32 bit multiplier will do 32 cycle generate 32 partial product
	begin
		// bi=0, bi-1=1 -> +A
		if(Product[0]==1'b0 && Mythicalbit ==1'b1) //Product 最低位為0 且 Mythicalbit 為1
		begin//做加: 把被乘數與 Product左半相加, 存回 Product左半
			Product = Product + {Mplicand,32'b0};
		end
		// bi=1, bi-1=0 -> -A
		if(Product[0]==1'b1 && Mythicalbit==1'b0)//Product 最低位為1 且 Mythicalbit 為0
		begin//做減: 把被乘數與 Product左半相減, 存回 Product左半
			Product = Product - {Mplicand,32'b0};
		end
		
		Mythicalbit = Product[0];
		
		Product = Product >>> 1;
		
	end 
	/* write down your design upon */
end

//判斷輸出
always @(posedge CLK or posedge RST)
begin
	if(RST)
		Product_Valid <=1'b0;
	else if(Counter==6'd32)
		Product_Valid <=1'b1;
	else
		Product_Valid <=1'b0;
end

endmodule

2019_DD_LAB10/labex/tb32mpy_booth_demo.v
`timescale 1ns/1ps
`include "32mpy_booth.v"

module tb_lab();
reg [31:0] in_a;
reg [31:0] in_b;
reg CLK;
reg reset;
wire [63:0] out;
wire out_valid;
reg [1:0] state;

reg [5:0]	count;
reg signed [64:0]	correct_ans;
reg error;
reg signed [63:0]	 temp_a;
reg signed [63:0]	temp_b;

lab m1(CLK, reset, in_a, in_b, out, out_valid, state);

initial begin
	$dumpfile("lab10.vcd");  //gtkwave
	$dumpvars;
	CLK = 1'b0;
	
	#10 reset = 1;//正數*正數
	temp_a = 32'd30;
	temp_b = 32'd90;
	state =2'd3;
	#20 reset = 0;
	
	#680 reset = 1;//正數*負數
	temp_a = 32'd30;
	temp_b = -32'd90;
	state =2'd1;
	#20 reset = 0;
	
	#680 reset = 1;//負數*正數
	temp_a = -32'd30;
	temp_b = 32'd90;
	state =2'd2;
	#20 reset = 0;
	
	#680 reset = 1;//負數*負數
	temp_a = -32'd30;
	temp_b = -32'd90;
	state =2'd3;
	#20 reset = 0;

	/*#680 reset = 1;//無號最大數*無號最大數
	temp_a = 64'd4294967295;
	temp_b = 64'd4294967295;
	#20 reset = 0;
	
	#680 reset = 1;//無號溢位數*1
	temp_a = 64'd4294967296;
	temp_b = 64'd1;
	#20 reset = 0;
	
	#680 reset = 1;//無號溢位數*1
	temp_a = 64'd4294967297;
	temp_b = 64'd1;
	#20 reset = 0;*/

	#680 $finish;
end

always #10 CLK = ~CLK;

always @(posedge CLK or posedge reset)
begin
	if(reset)//初始化
	begin
		count <= 0;
		in_a <= temp_a;
		in_b <= temp_b;
		correct_ans <= 0;
		error <= 0;
	end

	else//對答案
	begin
		if(state ==2'd3)
		correct_ans <= temp_a *temp_b;
		if(state ==2'd2)
		correct_ans <= temp_a *temp_a;
		if(state ==2'd1)
		correct_ans <= temp_b *temp_b;
		count <= count +1;

		if(out_valid==1)
			if($signed(out) != correct_ans)
			begin
				error <=1;
				$display ();
				$display ("// Fail //");
				$display ("//%d * %d = ?",temp_a, temp_b);
				$display ("//your answer is %d, but correct answer is %d\n",
				$signed(out), correct_ans);
			end
			
			else
			begin
				error <= 0;
				$display ();
				$display ("// Successful //");
				$display ("//%d * %d = ?",temp_a, temp_b);
				$display ("//your answer is %d,  correct answer is %d\n",
				$signed(out), correct_ans);
			end
	end
end

endmodule

2019_DD_LAB10/labex/lab10.vcd
$date
	Mon May 20 20:16:16 2019
$end
$version
	Icarus Verilog
$end
$timescale
	1ps
$end
$scope module tb_lab $end
$var wire 1 ! out_valid $end
$var wire 64 " out [63:0] $end
$var reg 1 # CLK $end
$var reg 65 $ correct_ans [64:0] $end
$var reg 6 % count [5:0] $end
$var reg 1 & error $end
$var reg 32 ' in_a [31:0] $end
$var reg 32 ( in_b [31:0] $end
$var reg 1 ) reset $end
$var reg 2 * state [1:0] $end
$var reg 64 + temp_a [63:0] $end
$var reg 64 , temp_b [63:0] $end
$scope module m1 $end
$var wire 1 # CLK $end
$var wire 1 ) RST $end
$var wire 32 - in_a [31:0] $end
$var wire 32 . in_b [31:0] $end
$var wire 2 / state [1:0] $end
$var reg 7 0 Counter [6:0] $end
$var reg 32 1 Mplicand [31:0] $end
$var reg 1 2 Mythicalbit $end
$var reg 64 3 Product [63:0] $end
$var reg 1 ! Product_Valid $end
$upscope $end
$upscope $end
$enddefinitions $end
#0
$dumpvars
bx 3
x2
bx 1
bx 0
bx /
bx .
bx -
bx ,
bx +
bx *
x)
bx (
bx '
x&
bx %
bx $
0#
bx "
x!
$end
#10000
b0 0
02
b0 1
b0 "
b0 3
0!
0&
b0 $
b1011010 (
b1011010 .
b11110 '
b11110 -
b0 %
1#
b11 *
b11 /
b1011010 ,
b11110 +
1)
#20000
0#
#30000
b1 %
b101010001100 $
b1011010 "
b1011010 3
b11110 1
b1 0
1#
0)
#40000
0#
#50000
b10 0
b10 %
b101101 "
b101101 3
1#
#60000
0#
#70000
b11 %
b11 0
12
b1111111111111111111111111111000100000000000000000000000000010110 "
b1111111111111111111111111111000100000000000000000000000000010110 3
1#
#80000
0#
#90000
b100 0
b100 %
02
b11110000000000000000000000000001011 "
b11110000000000000000000000000001011 3
1#
#100000
0#
#110000
b101 %
b101 0
12
b1111111111111111111111111111010011000000000000000000000000000101 "
b1111111111111111111111111111010011000000000000000000000000000101 3
1#
#120000
0#
#130000
b110 0
b110 %
b1111111111111111111111111111101001100000000000000000000000000010 "
b1111111111111111111111111111101001100000000000000000000000000010 3
1#
#140000
0#
#150000
b111 %
b111 0
02
b110000110000000000000000000000000001 "
b110000110000000000000000000000000001 3
1#
#160000
0#
#170000
b1000 0
b1000 %
12
b1111111111111111111111111111011100011000000000000000000000000000 "
b1111111111111111111111111111011100011000000000000000000000000000 3
1#
#180000
0#
#190000
b1001 %
b1001 0
02
b101010001100000000000000000000000000 "
b101010001100000000000000000000000000 3
1#
#200000
0#
#210000
b1010 0
b1010 %
b10101000110000000000000000000000000 "
b10101000110000000000000000000000000 3
1#
#220000
0#
#230000
b1011 %
b1011 0
b1010100011000000000000000000000000 "
b1010100011000000000000000000000000 3
1#
#240000
0#
#250000
b1100 0
b1100 %
b101010001100000000000000000000000 "
b101010001100000000000000000000000 3
1#
#260000
0#
#270000
b1101 %
b1101 0
b10101000110000000000000000000000 "
b10101000110000000000000000000000 3
1#
#280000
0#
#290000
b1110 0
b1110 %
b1010100011000000000000000000000 "
b1010100011000000000000000000000 3
1#
#300000
0#
#310000
b1111 %
b1111 0
b101010001100000000000000000000 "
b101010001100000000000000000000 3
1#
#320000
0#
#330000
b10000 0
b10000 %
b10101000110000000000000000000 "
b10101000110000000000000000000 3
1#
#340000
0#
#350000
b10001 %
b10001 0
b1010100011000000000000000000 "
b1010100011000000000000000000 3
1#
#360000
0#
#370000
b10010 0
b10010 %
b101010001100000000000000000 "
b101010001100000000000000000 3
1#
#380000
0#
#390000
b10011 %
b10011 0
b10101000110000000000000000 "
b10101000110000000000000000 3
1#
#400000
0#
#410000
b10100 0
b10100 %
b1010100011000000000000000 "
b1010100011000000000000000 3
1#
#420000
0#
#430000
b10101 %
b10101 0
b101010001100000000000000 "
b101010001100000000000000 3
1#
#440000
0#
#450000
b10110 0
b10110 %
b10101000110000000000000 "
b10101000110000000000000 3
1#
#460000
0#
#470000
b10111 %
b10111 0
b1010100011000000000000 "
b1010100011000000000000 3
1#
#480000
0#
#490000
b11000 0
b11000 %
b101010001100000000000 "
b101010001100000000000 3
1#
#500000
0#
#510000
b11001 %
b11001 0
b10101000110000000000 "
b10101000110000000000 3
1#
#520000
0#
#530000
b11010 0
b11010 %
b1010100011000000000 "
b1010100011000000000 3
1#
#540000
0#
#550000
b11011 %
b11011 0
b101010001100000000 "
b101010001100000000 3
1#
#560000
0#
#570000
b11100 0
b11100 %
b10101000110000000 "
b10101000110000000 3
1#
#580000
0#
#590000
b11101 %
b11101 0
b1010100011000000 "
b1010100011000000 3
1#
#600000
0#
#610000
b11110 0
b11110 %
b101010001100000 "
b101010001100000 3
1#
#620000
0#
#630000
b11111 %
b11111 0
b10101000110000 "
b10101000110000 3
1#
#640000
0#
#650000
b100000 0
b100000 %
b1010100011000 "
b1010100011000 3
1#
#660000
0#
#670000
b100001 %
1!
b100001 0
b101010001100 "
b101010001100 3
1#
#680000
0#
#690000
b100010 0
0!
b100010 %
1#
#700000
0#
#710000
b0 $
b11111111111111111111111110100110 (
b11111111111111111111111110100110 .
b0 %
b0 1
b0 "
b0 3
b0 0
1#
b1 *
b1 /
b1111111111111111111111111111111111111111111111111111111110100110 ,
1)
#720000
0#
#730000
b1 0
b11111111111111111111111110100110 "
b11111111111111111111111110100110 3
b11111111111111111111111110100110 1
b1 %
b1111110100100 $
1#
0)
#740000
0#
#750000
b10 %
b10 0
b1111111111111111111111111010011 "
b1111111111111111111111111010011 3
1#
#760000
0#
#770000
b11 0
b11 %
12
b10110100111111111111111111111111101001 "
b10110100111111111111111111111111101001 3
1#
#780000
0#
#790000
b100 %
b100 0
b1011010011111111111111111111111110100 "
b1011010011111111111111111111111110100 3
1#
#800000
0#
#810000
b101 0
b101 %
02
b1111111111111111111111111101111001001111111111111111111111111010 "
b1111111111111111111111111101111001001111111111111111111111111010 3
1#
#820000
0#
#830000
b110 %
b110 0
b1111111111111111111111111110111100100111111111111111111111111101 "
b1111111111111111111111111110111100100111111111111111111111111101 3
1#
#840000
0#
#850000
b111 0
b111 %
12
b10010010010011111111111111111111111110 "
b10010010010011111111111111111111111110 3
1#
#860000
0#
#870000
b1000 %
b1000 0
02
b1111111111111111111111111110010101001001111111111111111111111111 "
b1111111111111111111111111110010101001001111111111111111111111111 3
1#
#880000
0#
#890000
b1001 0
b1001 %
12
b1111110100100111111111111111111111111 "
b1111110100100111111111111111111111111 3
1#
#900000
0#
#910000
b1010 %
b1010 0
b111111010010011111111111111111111111 "
b111111010010011111111111111111111111 3
1#
#920000
0#
#930000
b1011 0
b1011 %
b11111101001001111111111111111111111 "
b11111101001001111111111111111111111 3
1#
#940000
0#
#950000
b1100 %
b1100 0
b1111110100100111111111111111111111 "
b1111110100100111111111111111111111 3
1#
#960000
0#
#970000
b1101 0
b1101 %
b111111010010011111111111111111111 "
b111111010010011111111111111111111 3
1#
#980000
0#
#990000
b1110 %
b1110 0
b11111101001001111111111111111111 "
b11111101001001111111111111111111 3
1#
#1000000
0#
#1010000
b1111 0
b1111 %
b1111110100100111111111111111111 "
b1111110100100111111111111111111 3
1#
#1020000
0#
#1030000
b10000 %
b10000 0
b111111010010011111111111111111 "
b111111010010011111111111111111 3
1#
#1040000
0#
#1050000
b10001 0
b10001 %
b11111101001001111111111111111 "
b11111101001001111111111111111 3
1#
#1060000
0#
#1070000
b10010 %
b10010 0
b1111110100100111111111111111 "
b1111110100100111111111111111 3
1#
#1080000
0#
#1090000
b10011 0
b10011 %
b111111010010011111111111111 "
b111111010010011111111111111 3
1#
#1100000
0#
#1110000
b10100 %
b10100 0
b11111101001001111111111111 "
b11111101001001111111111111 3
1#
#1120000
0#
#1130000
b10101 0
b10101 %
b1111110100100111111111111 "
b1111110100100111111111111 3
1#
#1140000
0#
#1150000
b10110 %
b10110 0
b111111010010011111111111 "
b111111010010011111111111 3
1#
#1160000
0#
#1170000
b10111 0
b10111 %
b11111101001001111111111 "
b11111101001001111111111 3
1#
#1180000
0#
#1190000
b11000 %
b11000 0
b1111110100100111111111 "
b1111110100100111111111 3
1#
#1200000
0#
#1210000
b11001 0
b11001 %
b111111010010011111111 "
b111111010010011111111 3
1#
#1220000
0#
#1230000
b11010 %
b11010 0
b11111101001001111111 "
b11111101001001111111 3
1#
#1240000
0#
#1250000
b11011 0
b11011 %
b1111110100100111111 "
b1111110100100111111 3
1#
#1260000
0#
#1270000
b11100 %
b11100 0
b111111010010011111 "
b111111010010011111 3
1#
#1280000
0#
#1290000
b11101 0
b11101 %
b11111101001001111 "
b11111101001001111 3
1#
#1300000
0#
#1310000
b11110 %
b11110 0
b1111110100100111 "
b1111110100100111 3
1#
#1320000
0#
#1330000
b11111 0
b11111 %
b111111010010011 "
b111111010010011 3
1#
#1340000
0#
#1350000
b100000 %
b100000 0
b11111101001001 "
b11111101001001 3
1#
#1360000
0#
#1370000
b100001 0
1!
b100001 %
b1111110100100 "
b1111110100100 3
1#
#1380000
0#
#1390000
b100010 %
0!
b100010 0
1#
#1400000
0#
#1410000
b0 0
02
b0 1
b0 "
b0 3
b0 $
b1011010 (
b1011010 .
b11111111111111111111111111100010 '
b11111111111111111111111111100010 -
b0 %
1#
b10 *
b10 /
b1011010 ,
b1111111111111111111111111111111111111111111111111111111111100010 +
1)
#1420000
0#
#1430000
b1 %
b1110000100 $
b11111111111111111111111111100010 "
b11111111111111111111111111100010 3
b11111111111111111111111111100010 1
b1 0
1#
0)
#1440000
0#
#1450000
b10 0
b10 %
b1111111111111111111111111110001 "
b1111111111111111111111111110001 3
1#
#1460000
0#
#1470000
b11 %
b11 0
12
b111100111111111111111111111111111000 "
b111100111111111111111111111111111000 3
1#
#1480000
0#
#1490000
b100 0
b100 %
02
b1111111111111111111111111111100010011111111111111111111111111100 "
b1111111111111111111111111111100010011111111111111111111111111100 3
1#
#1500000
0#
#1510000
b101 %
b101 0
b1111111111111111111111111111110001001111111111111111111111111110 "
b1111111111111111111111111111110001001111111111111111111111111110 3
1#
#1520000
0#
#1530000
b110 0
b110 %
b1111111111111111111111111111111000100111111111111111111111111111 "
b1111111111111111111111111111111000100111111111111111111111111111 3
1#
#1540000
0#
#1550000
b111 %
b111 0
12
b111000010011111111111111111111111111 "
b111000010011111111111111111111111111 3
1#
#1560000
0#
#1570000
b1000 0
b1000 %
b11100001001111111111111111111111111 "
b11100001001111111111111111111111111 3
1#
#1580000
0#
#1590000
b1001 %
b1001 0
b1110000100111111111111111111111111 "
b1110000100111111111111111111111111 3
1#
#1600000
0#
#1610000
b1010 0
b1010 %
b111000010011111111111111111111111 "
b111000010011111111111111111111111 3
1#
#1620000
0#
#1630000
b1011 %
b1011 0
b11100001001111111111111111111111 "
b11100001001111111111111111111111 3
1#
#1640000
0#
#1650000
b1100 0
b1100 %
b1110000100111111111111111111111 "
b1110000100111111111111111111111 3
1#
#1660000
0#
#1670000
b1101 %
b1101 0
b111000010011111111111111111111 "
b111000010011111111111111111111 3
1#
#1680000
0#
#1690000
b1110 0
b1110 %
b11100001001111111111111111111 "
b11100001001111111111111111111 3
1#
#1700000
0#
#1710000
b1111 %
b1111 0
b1110000100111111111111111111 "
b1110000100111111111111111111 3
1#
#1720000
0#
#1730000
b10000 0
b10000 %
b111000010011111111111111111 "
b111000010011111111111111111 3
1#
#1740000
0#
#1750000
b10001 %
b10001 0
b11100001001111111111111111 "
b11100001001111111111111111 3
1#
#1760000
0#
#1770000
b10010 0
b10010 %
b1110000100111111111111111 "
b1110000100111111111111111 3
1#
#1780000
0#
#1790000
b10011 %
b10011 0
b111000010011111111111111 "
b111000010011111111111111 3
1#
#1800000
0#
#1810000
b10100 0
b10100 %
b11100001001111111111111 "
b11100001001111111111111 3
1#
#1820000
0#
#1830000
b10101 %
b10101 0
b1110000100111111111111 "
b1110000100111111111111 3
1#
#1840000
0#
#1850000
b10110 0
b10110 %
b111000010011111111111 "
b111000010011111111111 3
1#
#1860000
0#
#1870000
b10111 %
b10111 0
b11100001001111111111 "
b11100001001111111111 3
1#
#1880000
0#
#1890000
b11000 0
b11000 %
b1110000100111111111 "
b1110000100111111111 3
1#
#1900000
0#
#1910000
b11001 %
b11001 0
b111000010011111111 "
b111000010011111111 3
1#
#1920000
0#
#1930000
b11010 0
b11010 %
b11100001001111111 "
b11100001001111111 3
1#
#1940000
0#
#1950000
b11011 %
b11011 0
b1110000100111111 "
b1110000100111111 3
1#
#1960000
0#
#1970000
b11100 0
b11100 %
b111000010011111 "
b111000010011111 3
1#
#1980000
0#
#1990000
b11101 %
b11101 0
b11100001001111 "
b11100001001111 3
1#
#2000000
0#
#2010000
b11110 0
b11110 %
b1110000100111 "
b1110000100111 3
1#
#2020000
0#
#2030000
b11111 %
b11111 0
b111000010011 "
b111000010011 3
1#
#2040000
0#
#2050000
b100000 0
b100000 %
b11100001001 "
b11100001001 3
1#
#2060000
0#
#2070000
b100001 %
1!
b100001 0
b1110000100 "
b1110000100 3
1#
#2080000
0#
#2090000
b100010 0
0!
b100010 %
1#
#2100000
0#
#2110000
b0 $
b11111111111111111111111110100110 (
b11111111111111111111111110100110 .
b0 %
02
b0 1
b0 "
b0 3
b0 0
1#
b11 *
b11 /
b1111111111111111111111111111111111111111111111111111111110100110 ,
1)
#2120000
0#
#2130000
b1 0
b11111111111111111111111110100110 "
b11111111111111111111111110100110 3
b11111111111111111111111111100010 1
b1 %
b101010001100 $
1#
0)
#2140000
0#
#2150000
b10 %
b10 0
b1111111111111111111111111010011 "
b1111111111111111111111111010011 3
1#
#2160000
0#
#2170000
b11 0
b11 %
12
b111100111111111111111111111111101001 "
b111100111111111111111111111111101001 3
1#
#2180000
0#
#2190000
b100 %
b100 0
b11110011111111111111111111111110100 "
b11110011111111111111111111111110100 3
1#
#2200000
0#
#2210000
b101 0
b101 %
02
b1111111111111111111111111111010011001111111111111111111111111010 "
b1111111111111111111111111111010011001111111111111111111111111010 3
1#
#2220000
0#
#2230000
b110 %
b110 0
b1111111111111111111111111111101001100111111111111111111111111101 "
b1111111111111111111111111111101001100111111111111111111111111101 3
1#
#2240000
0#
#2250000
b111 0
b111 %
12
b110000110011111111111111111111111110 "
b110000110011111111111111111111111110 3
1#
#2260000
0#
#2270000
b1000 %
b1000 0
02
b1111111111111111111111111111011100011001111111111111111111111111 "
b1111111111111111111111111111011100011001111111111111111111111111 3
1#
#2280000
0#
#2290000
b1001 0
b1001 %
12
b101010001100111111111111111111111111 "
b101010001100111111111111111111111111 3
1#
#2300000
0#
#2310000
b1010 %
b1010 0
b10101000110011111111111111111111111 "
b10101000110011111111111111111111111 3
1#
#2320000
0#
#2330000
b1011 0
b1011 %
b1010100011001111111111111111111111 "
b1010100011001111111111111111111111 3
1#
#2340000
0#
#2350000
b1100 %
b1100 0
b101010001100111111111111111111111 "
b101010001100111111111111111111111 3
1#
#2360000
0#
#2370000
b1101 0
b1101 %
b10101000110011111111111111111111 "
b10101000110011111111111111111111 3
1#
#2380000
0#
#2390000
b1110 %
b1110 0
b1010100011001111111111111111111 "
b1010100011001111111111111111111 3
1#
#2400000
0#
#2410000
b1111 0
b1111 %
b101010001100111111111111111111 "
b101010001100111111111111111111 3
1#
#2420000
0#
#2430000
b10000 %
b10000 0
b10101000110011111111111111111 "
b10101000110011111111111111111 3
1#
#2440000
0#
#2450000
b10001 0
b10001 %
b1010100011001111111111111111 "
b1010100011001111111111111111 3
1#
#2460000
0#
#2470000
b10010 %
b10010 0
b101010001100111111111111111 "
b101010001100111111111111111 3
1#
#2480000
0#
#2490000
b10011 0
b10011 %
b10101000110011111111111111 "
b10101000110011111111111111 3
1#
#2500000
0#
#2510000
b10100 %
b10100 0
b1010100011001111111111111 "
b1010100011001111111111111 3
1#
#2520000
0#
#2530000
b10101 0
b10101 %
b101010001100111111111111 "
b101010001100111111111111 3
1#
#2540000
0#
#2550000
b10110 %
b10110 0
b10101000110011111111111 "
b10101000110011111111111 3
1#
#2560000
0#
#2570000
b10111 0
b10111 %
b1010100011001111111111 "
b1010100011001111111111 3
1#
#2580000
0#
#2590000
b11000 %
b11000 0
b101010001100111111111 "
b101010001100111111111 3
1#
#2600000
0#
#2610000
b11001 0
b11001 %
b10101000110011111111 "
b10101000110011111111 3
1#
#2620000
0#
#2630000
b11010 %
b11010 0
b1010100011001111111 "
b1010100011001111111 3
1#
#2640000
0#
#2650000
b11011 0
b11011 %
b101010001100111111 "
b101010001100111111 3
1#
#2660000
0#
#2670000
b11100 %
b11100 0
b10101000110011111 "
b10101000110011111 3
1#
#2680000
0#
#2690000
b11101 0
b11101 %
b1010100011001111 "
b1010100011001111 3
1#
#2700000
0#
#2710000
b11110 %
b11110 0
b101010001100111 "
b101010001100111 3
1#
#2720000
0#
#2730000
b11111 0
b11111 %
b10101000110011 "
b10101000110011 3
1#
#2740000
0#
#2750000
b100000 %
b100000 0
b1010100011001 "
b1010100011001 3
1#
#2760000
0#
#2770000
b100001 0
1!
b100001 %
b101010001100 "
b101010001100 3
1#
#2780000
0#
#2790000
b100010 %
0!
b100010 0
1#
#2800000
0#
#2810000
b100011 0
b100011 %
1#
